nm25/__init__.py
nm25/main.py
nm25/data/mt/adam_bashford_2.py
nm25/data/mt/adam_moulton.py
nm25/data/mt/adams_bashford_3.py
nm25/data/mt/adams_bashford_4.py
nm25/data/mt/calculate_freqs.py
nm25/data/mt/dft_and_idfft_zadanie.py
nm25/data/mt/dft_cutoff_5gz.py
nm25/data/mt/dft_idft.py
nm25/data/mt/fft_spektr_chastot.py
nm25/data/mt/koshi_metodom_eulera.py
nm25/data/mt/koshi_runge_adam.py
nm25/data/mt/metod_razvert.py
nm25/data/mt/predictor_corrector.py
nm25/data/mt/qr_algorithm.py
nm25/data/mt/runge_kutta_1.py
nm25/data/mt/runge_kutta_2.py
nm25/data/mt/runge_kutta_3.py
nm25/data/mt/runge_kutta_4.py
nm25/data/pr/num1.py
nm25/data/pr/num10.py
nm25/data/pr/num11.py
nm25/data/pr/num16.py
nm25/data/pr/num17.py
nm25/data/pr/num18.py
nm25/data/pr/num19.py
nm25/data/pr/num21.py
nm25/data/pr/num29.py
nm25/data/pr/num3.py
nm25/data/pr/num31.py
nm25/data/pr/num32.py
nm25/data/pr/num5.py
nm25/data/pr/num6.py
nm25/data/pr/num7.py
nm25/data/th/num1.md
nm25/data/th/num10.md
nm25/data/th/num11.md
nm25/data/th/num12.md
nm25/data/th/num13.md
nm25/data/th/num14.md
nm25/data/th/num15.md
nm25/data/th/num16.md
nm25/data/th/num17.md
nm25/data/th/num18.md
nm25/data/th/num19.md
nm25/data/th/num2.md
nm25/data/th/num20.md
nm25/data/th/num21.md
nm25/data/th/num22.md
nm25/data/th/num23.md
nm25/data/th/num24.md
nm25/data/th/num25.md
nm25/data/th/num26.md
nm25/data/th/num27.md
nm25/data/th/num28.md
nm25/data/th/num29.md
nm25/data/th/num3.md
nm25/data/th/num30.md
nm25/data/th/num31.md
nm25/data/th/num32.md
nm25/data/th/num4.md
nm25/data/th/num5.md
nm25/data/th/num6.md
nm25/data/th/num7.md
nm25/data/th/num8.md
nm25/data/th/num9.md
nm25-1.6.dist-info/METADATA
nm25-1.6.dist-info/WHEEL
nm25-1.6.dist-info/top_level.txt
nm25-1.6.dist-info/RECORD
